brish/__init__.py
brish/__main__.py
brish/brish.zsh
brish/brish2.zsh
brish/brishmod.py
brish/brishz.py
brish-0.3.5.dist-info/WHEEL
brish-0.3.5.dist-info/METADATA
brish-0.3.5.dist-info/RECORD
