Metadata-Version: 2.1
Name: brish
Version: 0.3.5
Summary: A bridge between zsh and Python.
Home-page: https://github.com/NightMachinary/brish
Author: NightMachinary
Author-email: rudiwillalwaysloveyou@gmail.com
Requires-Python: >=3.7.0,<4.0.0
Classifier: Programming Language :: Python :: 3
Classifier: Programming Language :: Python :: 3.7
Classifier: Programming Language :: Python :: 3.8
Classifier: Programming Language :: Python :: 3.9
Classifier: Programming Language :: Python :: 3.10
Classifier: Programming Language :: Python :: 3.11
Requires-Dist: icecream (>=2.1.0,<3.0.0)
Project-URL: Repository, https://github.com/NightMachinary/brish
